Metadata-Version: 1.1
Name: PigLatinTranslation
Version: 0.1.11
Summary: A Pig Latin Translation Microservice
Home-page: https://github.com/Jai-Chaudhary/pig-latin-translation-microservice
Author: Jai Chaudhary
Author-email: jai.chaudhary.ittd@gmail.com
License: MIT
Platform: UNKNOWN
Classifier: Development Status :: 3 - Alpha
